config_reg/__init__.py
config_reg/callback.py
config_reg/convert.py
config_reg/if_yaml.py
config_reg/index.py
config_reg/reg.py
config_reg/type_def.py
config_reg/type_transform.py
config_reg/util/__init__.py
config_reg/util/subst_util.py
config_reg-0.1.6.dist-info/licenses/LICENSE.md
config_reg-0.1.6.dist-info/METADATA
config_reg-0.1.6.dist-info/WHEEL
config_reg-0.1.6.dist-info/top_level.txt
config_reg-0.1.6.dist-info/RECORD
