Metadata-Version: 2.4
Name: config_reg
Version: 0.1.6
Summary: personal config_reg project
Author-email: kelvin34501 <kelvin34501@foxmail.com>
Maintainer-email: kelvin34501 <kelvin34501@foxmail.com>
License: # GNU GENERAL PUBLIC LICENSE
Project-URL: Homepage, https://github.com/kelvin34501/config_reg
Keywords: config,argparse
Classifier: Development Status :: 2 - Pre-Alpha
Classifier: Intended Audience :: Developers
Classifier: Topic :: Software Development
Classifier: License :: OSI Approved :: GNU General Public License v3 or later (GPLv3+)
Classifier: Programming Language :: Python :: 3
Classifier: Programming Language :: Python :: 3.8
Classifier: Programming Language :: Python :: 3.9
Classifier: Programming Language :: Python :: 3.10
Classifier: Programming Language :: Python :: 3.11
Classifier: Programming Language :: Python :: 3 :: Only
Requires-Python: >=3.8
License-File: LICENSE.md
Requires-Dist: PyYAML
Dynamic: license-file
